pyaibrain/client/.env
pyaibrain/client/GUI.py
pyaibrain/client/__init__.py
pyaibrain/server/.env
pyaibrain/server/__init__.py
pythonaibrain_client-1.0.4.dist-info/licenses/LICENSE.txt
pythonaibrain_client-1.0.4.dist-info/METADATA
pythonaibrain_client-1.0.4.dist-info/WHEEL
pythonaibrain_client-1.0.4.dist-info/entry_points.txt
pythonaibrain_client-1.0.4.dist-info/top_level.txt
pythonaibrain_client-1.0.4.dist-info/RECORD
