Metadata-Version: 2.4
Name: pythonaibrain-client
Version: 1.0.4
Summary: TIGER AI secure encrypted socket client powered by pythonaibrain
Author-email: Divyanshu Sinha <divyanshu.sinha136@gmail.com>
Requires-Python: >=3.8
License-File: LICENSE.txt
Requires-Dist: python-dotenv>=1.0.0
Requires-Dist: rich
Requires-Dist: prompt-toolkit
Dynamic: license-file
